lounger/__init__.py
lounger/analyze_cases.py
lounger/case.py
lounger/centrifuge/__init__.py
lounger/centrifuge/centrifuge_client.py
lounger/centrifuge/centrifuge_client_factory.py
lounger/centrifuge/centrifuge_manager.py
lounger/cli.py
lounger/commons/__init__.py
lounger/commons/assert_result.py
lounger/commons/extract.py
lounger/commons/load_config.py
lounger/commons/model.py
lounger/commons/template_engine.py
lounger/config.py
lounger/db_operation/__init__.py
lounger/db_operation/base_db.py
lounger/db_operation/mongo_db.py
lounger/db_operation/mssql_db.py
lounger/db_operation/mysql_db.py
lounger/db_operation/postgres_db.py
lounger/db_operation/sqlite_db.py
lounger/libs/__init__.py
lounger/libs/jsonpath.py
lounger/log.py
lounger/plugin.py
lounger/po.py
lounger/project_temp/__init__.py
lounger/project_temp/api/config/config.yaml
lounger/project_temp/api/datas/sample/test_sample.yaml
lounger/project_temp/api/pytest.ini
lounger/project_temp/api/test_api.py
lounger/project_temp/api/test_dir/test_sample.py
lounger/project_temp/conftest.py
lounger/project_temp/web/pytest.ini
lounger/project_temp/web/test_dir/test_sample.py
lounger/pytest_extend/__init__.py
lounger/pytest_extend/conversion.py
lounger/pytest_extend/params.py
lounger/pytest_extend/screenshot.py
lounger/request/__init__.py
lounger/request/request_client.py
lounger/request/request_utils.py
lounger/testdata/__init__.py
lounger/testdata/random_data.py
lounger/testdata/random_func.py
lounger/utils/__init__.py
lounger/utils/cache.py
lounger/utils/cache_data.json
lounger/utils/config_utils.py
lounger/utils/dependence.py
lounger/utils/resource_loader.py
lounger/utils/variables.py
lounger/utils/webhook.py
lounger-0.8.0.dist-info/entry_points.txt
lounger-0.8.0.dist-info/licenses/LICENSE
lounger-0.8.0.dist-info/METADATA
lounger-0.8.0.dist-info/WHEEL
lounger-0.8.0.dist-info/RECORD
