Metadata-Version: 2.4
Name: lounger
Version: 0.8.0
Summary: Next generation automated testing framework.
License-File: LICENSE
Author: bugmaster
Author-email: defnngj@gmail.com
Requires-Python: >=3.9
Classifier: Programming Language :: Python :: 3
Classifier: Programming Language :: Python :: 3.9
Classifier: Programming Language :: Python :: 3.10
Classifier: Programming Language :: Python :: 3.11
Classifier: Programming Language :: Python :: 3.12
Classifier: Programming Language :: Python :: 3.13
Classifier: Programming Language :: Python :: 3.14
Requires-Dist: PyMySQL (>=1.1.1,<2.0.0)
Requires-Dist: PyYAML (>=6.0.2,<7.0.0)
Requires-Dist: centrifuge-python (>=0.4.1,<0.5.0)
Requires-Dist: click (>=8.1.7,<9.0.0)
Requires-Dist: openpyxl (>=3.1.5,<3.2.0)
Requires-Dist: pytest-playwright (>=0.7.0,<0.8.0)
Requires-Dist: pytest-req (>=0.5.0)
Requires-Dist: pytest-rerunfailures (>=14.0,<15.0)
Requires-Dist: pytest-xhtml (>=0.3.0)
Requires-Dist: python-dateutil (==2.8.2)
Project-URL: Homepage, https://github.com/SeldomQA/lounger
Project-URL: Repository, https://github.com/SeldomQA/lounger
